grascii_gui/__about__.py
grascii_gui/__init__.py
grascii_gui/__main__.py
grascii_gui/app.py
grascii_gui-0.2.0.dist-info/METADATA
grascii_gui-0.2.0.dist-info/WHEEL
grascii_gui-0.2.0.dist-info/entry_points.txt
grascii_gui-0.2.0.dist-info/licenses/LICENSE.txt
grascii_gui-0.2.0.dist-info/RECORD
