Metadata-Version: 2.1
Name: grascii-gui
Version: 0.2.0
Summary: A graphical interface for Grascii Search
Project-URL: Documentation, https://github.com/grascii/grascii-gui
Project-URL: Issues, https://github.com/grascii/grascii-gui/issues
Project-URL: Source, https://github.com/grascii/grascii-gui
Author-email: Chanic Panic <dev@chanicpanic.com>
Classifier: Development Status :: 4 - Beta
Classifier: Programming Language :: Python
Classifier: Programming Language :: Python :: 3.7
Classifier: Programming Language :: Python :: 3.8
Classifier: Programming Language :: Python :: 3.9
Classifier: Programming Language :: Python :: 3.10
Classifier: Programming Language :: Python :: Implementation :: CPython
Classifier: Programming Language :: Python :: Implementation :: PyPy
Requires-Python: >=3.7
Requires-Dist: grascii~=0.5.0
